furiosa/sdk/__init__.py
furiosa/sdk/py.typed
furiosa_sdk-0.10.2.dist-info/WHEEL
furiosa_sdk-0.10.2.dist-info/METADATA
furiosa_sdk-0.10.2.dist-info/RECORD
