Metadata-Version: 2.1
Name: furiosa-sdk
Version: 0.10.2
Summary: Furiosa SDK
Author-email: "FurioaAI, Inc." <pkg@furiosa.ai>
Requires-Python: ~=3.8
Classifier: Development Status :: 4 - Beta
Classifier: Environment :: Console
Classifier: Intended Audience :: Developers
Classifier: Intended Audience :: System Administrators
Classifier: License :: OSI Approved :: Apache Software License
Classifier: Programming Language :: Python :: 3
Classifier: Programming Language :: Python :: 3.8
Classifier: Programming Language :: Python :: 3.9
Classifier: Programming Language :: Python :: 3.10
Classifier: Topic :: Software Development :: Libraries :: Python Modules
Classifier: Topic :: Scientific/Engineering :: Artificial Intelligence
Requires-Dist: furiosa-cli == 0.10.*
Requires-Dist: furiosa-runtime == 0.10.*
Requires-Dist: furiosa-tools == 0.10.*
Requires-Dist: furiosa-cli == 0.10.* ; extra == "cli"
Requires-Dist: furiosa-device == 0.10.* ; extra == "device"
Requires-Dist: furiosa-cli == 0.10.* ; extra == "full"
Requires-Dist: furiosa-litmus == 0.10.* ; extra == "full"
Requires-Dist: furiosa-optimizer == 0.10.* ; extra == "full"
Requires-Dist: furiosa-quantizer == 0.10.* ; extra == "full"
Requires-Dist: furiosa-server == 0.10.* ; extra == "full"
Requires-Dist: furiosa-serving == 0.10.* ; extra == "full"
Requires-Dist: furiosa-tools == 0.10.* ; extra == "full"
Requires-Dist: furiosa-device == 0.10.* ; extra == "full"
Requires-Dist: furiosa-litmus == 0.10.* ; extra == "litmus"
Requires-Dist: furiosa-optimizer == 0.10.* ; extra == "quantizer"
Requires-Dist: furiosa-quantizer == 0.10.* ; extra == "quantizer"
Requires-Dist: furiosa-server == 0.10.* ; extra == "server"
Requires-Dist: furiosa-serving == 0.10.* ; extra == "serving"
Requires-Dist: mypy ; extra == "test"
Requires-Dist: pytest ; extra == "test"
Requires-Dist: ruff ; extra == "test"
Requires-Dist: furiosa-tools == 0.10.* ; extra == "tool"
Project-URL: Bug Tracker, https://github.com/furiosa-ai/furiosa-sdk/issues
Project-URL: Documentation, https://furiosa-ai.github.io/docs
Project-URL: Home, https://furiosa.ai
Project-URL: Source Code, https://github.com/furiosa-ai/furiosa-sdk
Provides-Extra: cli
Provides-Extra: device
Provides-Extra: full
Provides-Extra: litmus
Provides-Extra: quantizer
Provides-Extra: server
Provides-Extra: serving
Provides-Extra: test
Provides-Extra: tool
